[
  {
    "name": "FAISAL HABIB",
    "father_name": "HABIB UR REHMAN",
    "cnic": "36302-9193847-5",
    "personal_no": 31795665,
    "cell_no": "0302-7701771",
    "imei": "868475032116019",
    "device": "SMART Phone",
    "address": "House # 3730/1 near noshab cinema Railway Road Multan",
    "dob": "13-03-87",
    "markaz": "CHAK RS",
    "doj": "2017-06-07",
    "tehsil": "SHUJABAD",
    "charge": "Permanent"
  },
  {
    "name": "Muhammad Kashif Rabbani",
    "father_name": "Ghulam Abbas",
    "cnic": "36302-2943428-7",
    "personal_no": 32000327,
    "cell_no": "0345-7214817",
    "imei": "863503045102992",
    "device": "Smart Phone",
    "address": "Moza Khadal, P/O Jhoke Wains, Bosan Road. Multan",
    "dob": 32264,
    "markaz": "Sikandarabad ",
    "doj": "2017-06-07",
    "tehsil": "SHUJABAD",
    "charge": "Permanent"
  },
  {
    "name": "Aamer saeed",
    "father_name": "Muhammad Ameen",
    "cnic": "36303-7492826-5",
    "personal_no": 31638781,
    "cell_no": "0302-7477145",
    "imei": "864098035113264",
    "device": "Smart Phone",
    "address": "Chah Jhit Wala Mouza alamgir   old shujabad road Multan ",
    "dob": 33883,
    "markaz": "Matotli",
    "doj": "2017-06-07",
    "tehsil": "Shujabad",
    "charge": "Permanent"
  },
  {
    "name": "Junaid Naeem",
    "father_name": "Abdul Naeem",
    "cnic": "36302-8057631-9",
    "personal_no": 31843041,
    "cell_no": "0307-6689882",
    "imei": "355307076978766",
    "device": "Smart Phone",
    "address": "Gulshan e faiz colony house #11-A street # 02 Qasim pur multan",
    "dob": 34214,
    "markaz": "Maraha",
    "doj": "2017-06-07",
    "tehsil": "Shujabad",
    "charge": "Permanent"
  },
  {
    "name": "Aamir Saleem ",
    "father_name": "Muhammad Saleem ",
    "cnic": "36304-6491523-5",
    "personal_no": 32007905,
    "cell_no": "0300-7085237",
    "imei": "864836033771793",
    "device": "Smart Phone",
    "address": "House # 289/D lal bagh Shujabad ",
    "dob": "22/01/1992",
    "markaz": "Basti Mithu ",
    "doj": "2017-06-07",
    "tehsil": "Shujabad",
    "charge": "Permanent"
  },
  {
    "name": "SIDRA NOUREEN",
    "father_name": "Muhammad Aslam",
    "cnic": "31203-9759651-4",
    "personal_no": 32068531,
    "cell_no": "0331-2020150",
    "imei": "861335043248259",
    "device": "SMART Phone",
    "address": "H # 83, Green view society, near Bahawalpur bypass, Multan.",
    "dob": "11.08.1993",
    "markaz": "TODAR PUR",
    "doj": "01.03.2018",
    "tehsil": "SHUJABAD",
    "charge": "Permanent"
  },
  {
    "name": "ATIF MEHMOOD ",
    "father_name": "HAJI GHULAM MUSTAFA ",
    "cnic": "36304-0278897-5",
    "personal_no": 31863779,
    "cell_no": "0346-7040094",
    "imei": 355248086428188,
    "device": "smart phone\n",
    "address": "House# 164-D Rajput colony shujabad",
    "dob": "24-10-92",
    "markaz": "Rasool pur",
    "doj": "2017-06-07",
    "tehsil": "SHUJABAD",
    "charge": "Permanent"
  },
  {
    "name": "Muhammad Kamran Shair",
    "father_name": "Shair Muhammad",
    "cnic": "36304-4575559-7",
    "personal_no": 31555927,
    "cell_no": "0304-5964248",
    "imei": 869130036181472,
    "device": "Smart Phone",
    "address": "Cha jom Kha wala",
    "dob": 32967,
    "markaz": "Thath Ghalwan",
    "doj": "2017-06-07",
    "tehsil": "Shujabad",
    "charge": "Permanent"
  },
  {
    "name": "Asif Mehmood Madni",
    "father_name": "Muhammad Aslam",
    "cnic": "36304-3002313-5",
    "personal_no": 32011663,
    "cell_no": "0301-7416914",
    "imei": "868484050617072'",
    "device": "smart phone",
    "address": "Faiz Colony Shujabad",
    "dob": "15.03.1990",
    "markaz": "GARDEZ PUR",
    "doj": "06.07.2017",
    "tehsil": "SHUJABAD",
    "charge": "Permanent"
  },
  {
    "name": "Sadaf Akram",
    "father_name": "Muhammad Akram",
    "cnic": "36304-2263234-2",
    "personal_no": 31884936,
    "cell_no": 3238621758,
    "imei": "354619079869821/01",
    "device": "smart phone",
    "address": "MUHALLA ASAD KHAN WALA SHUJABAD",
    "dob": "15-2-1993",
    "markaz": "SHUJABAD",
    "doj": "2017-06-07",
    "tehsil": "SHUJABAD",
    "charge": "Permanent"
  },
  {
    "name": "Muzammil Hussaun",
    "father_name": "Abdullah Shah",
    "cnic": "36304-2395336-1",
    "personal_no": 31764145,
    "cell_no": "0321-5894820",
    "imei": "860369038518377",
    "device": "smart phone",
    "address": "outside bab e umar farooq near gps asad khanwala shujabad",
    "dob": "20-02-1986",
    "markaz": "Punjani",
    "doj": "2017-06-07",
    "tehsil": "SHUJABAD",
    "charge": "Permanent"
  },
  {
    "name": "Naila Aslam",
    "father_name": "Muhammad Aslam Nasir",
    "cnic": "36304-7098482-2",
    "personal_no": 31976094,
    "cell_no": 3008810567,
    "imei": "353395093212584",
    "device": "smart phone",
    "address": "New housing colony shujbad.\n",
    "dob": 33239,
    "markaz": "Zareef Shaheed",
    "doj": "2017-06-07",
    "tehsil": "shujabad",
    "charge": "permanent"
  }
]